{"nodes": [{"id": "calendrier_calendrierpage", "label": "CalendrierPage", "file_type": "code", "source_file": "app/agent/calendrier/page.tsx", "source_location": null, "source_url": null, "captured_at": null, "author": null, "contributor": null}, {"id": "calendrier_rdvcard", "label": "RdvCard", "file_type": "code", "source_file": "app/agent/calendrier/page.tsx", "source_location": null, "source_url": null, "captured_at": null, "author": null, "contributor": null}, {"id": "calendrier_rdv", "label": "RDV", "file_type": "code", "source_file": "app/agent/calendrier/page.tsx", "source_location": null, "source_url": null, "captured_at": null, "author": null, "contributor": null}], "edges": [{"source": "calendrier_calendrierpage", "target": "calendrier_rdvcard", "relation": "calls", "confidence": "EXTRACTED", "confidence_score": 1.0, "source_file": "app/agent/calendrier/page.tsx", "source_location": null, "weight": 1.0}, {"source": "calendrier_calendrierpage", "target": "calendrier_rdv", "relation": "references", "confidence": "EXTRACTED", "confidence_score": 1.0, "source_file": "app/agent/calendrier/page.tsx", "source_location": null, "weight": 1.0}, {"source": "calendrier_rdvcard", "target": "calendrier_rdv", "relation": "references", "confidence": "EXTRACTED", "confidence_score": 1.0, "source_file": "app/agent/calendrier/page.tsx", "source_location": null, "weight": 1.0}, {"source": "calendrier_calendrierpage", "target": "hub_agenthubage", "relation": "references", "confidence": "EXTRACTED", "confidence_score": 1.0, "source_file": "app/agent/calendrier/page.tsx", "source_location": null, "weight": 1.0}], "hyperedges": []}