{"nodes": [{"id": "trialbanner_trialbanner", "label": "TrialBanner", "file_type": "code", "source_file": "components/TrialBanner.tsx", "source_location": null, "source_url": null, "captured_at": null, "author": null, "contributor": null}], "edges": [{"source": "trialbanner_trialbanner", "target": "lib_supabaseclient_supabase", "relation": "calls", "confidence": "EXTRACTED", "confidence_score": 1.0, "source_file": "components/TrialBanner.tsx", "source_location": "line 4", "weight": 1.0}, {"source": "trialbanner_trialbanner", "target": "stripe_payment_link", "relation": "references", "confidence": "EXTRACTED", "confidence_score": 1.0, "source_file": "components/TrialBanner.tsx", "source_location": "line 7", "weight": 1.0}, {"source": "trialbanner_trialbanner", "target": "agentlanding_agentlanding", "relation": "conceptually_related_to", "confidence": "INFERRED", "confidence_score": 0.7, "source_file": "components/TrialBanner.tsx", "source_location": null, "weight": 0.7}], "hyperedges": []}